{
  "version": "1.0",
  "card": "Yamato (OP16-079) (V.2)",
  "set": " The Time of Battle (Asia Region Legal) - Singles",
  "canonical_name": "OnePiece_Products_Singles_The-Time-of-Battle-Asia-Region-Legal_Yamato-OP16-079-V2",
  "image": "data/images/OnePiece_Products_Singles_The-Time-of-Battle-Asia-Region-Legal_Yamato-OP16-079-V2.jpg",
  "languages": [
    "S-Chinese",
    "Japanese",
    "Korean"
  ],
  "only_germany": false,
  "available": 8,
  "sold": 3,
  "inserted": 1,
  "listings": [
    {
      "card": "Yamato (OP16-079) (V.2)",
      "canonical_name": "OnePiece_Products_Singles_The-Time-of-Battle-Asia-Region-Legal_Yamato-OP16-079-V2",
      "seller": {
        "name": "19Rico85",
        "country": "Item location: Germany"
      },
      "language": "S-Chinese",
      "price": 60.0,
      "quantity": 2,
      "condition": "NM",
      "comment": "",
      "date": 1782108289.4037144,
      "ended": false,
      "new": false,
      "previous_prices": [
        [
          100.0,
          1781911230.1831412
        ]
      ],
      "previous_quantities": [],
      "first_date": 1781809102.7223003,
      "last_date": 0.0,
      "price_is_new": true,
      "quantity_change": 0,
      "first_ed": 0,
      "reverse_holo": 0,
      "archived": false
    },
    {
      "card": "Yamato (OP16-079) (V.2)",
      "canonical_name": "OnePiece_Products_Singles_The-Time-of-Battle-Asia-Region-Legal_Yamato-OP16-079-V2",
      "seller": {
        "name": "Trip0losk1i",
        "country": "Item location: Italy"
      },
      "language": "Japanese",
      "price": 78.0,
      "quantity": 0,
      "condition": "NM",
      "comment": "",
      "date": 1781911230.1831412,
      "ended": true,
      "new": true,
      "previous_prices": [
        [
          95.0,
          1781809102.7223003
        ]
      ],
      "previous_quantities": [
        [
          1,
          1781911230.1831412
        ]
      ],
      "first_date": 1781809102.7223003,
      "last_date": 0.0,
      "price_is_new": false,
      "quantity_change": -1,
      "first_ed": 0,
      "reverse_holo": 0,
      "archived": false
    },
    {
      "card": "Yamato (OP16-079) (V.2)",
      "canonical_name": "OnePiece_Products_Singles_The-Time-of-Battle-Asia-Region-Legal_Yamato-OP16-079-V2",
      "seller": {
        "name": "Massmasmoo321",
        "country": "Item location: France"
      },
      "language": "Japanese",
      "price": 79.99,
      "quantity": 0,
      "condition": "NM",
      "comment": "Sleeve-Toploader",
      "date": 1781911230.1831412,
      "ended": true,
      "new": true,
      "previous_prices": [],
      "previous_quantities": [
        [
          1,
          1781911230.1831412
        ]
      ],
      "first_date": 1781809102.7223003,
      "last_date": 0.0,
      "price_is_new": false,
      "quantity_change": -1,
      "first_ed": 0,
      "reverse_holo": 0,
      "archived": false
    },
    {
      "card": "Yamato (OP16-079) (V.2)",
      "canonical_name": "OnePiece_Products_Singles_The-Time-of-Battle-Asia-Region-Legal_Yamato-OP16-079-V2",
      "seller": {
        "name": "Max2005",
        "country": "Item location: Germany"
      },
      "language": "Japanese",
      "price": 80.0,
      "quantity": 0,
      "condition": "NM",
      "comment": "Shipping only in Germany",
      "date": 1781911230.1831412,
      "ended": true,
      "new": true,
      "previous_prices": [
        [
          85.0,
          1781809102.7223003
        ]
      ],
      "previous_quantities": [
        [
          1,
          1781911230.1831412
        ]
      ],
      "first_date": 1781809102.7223003,
      "last_date": 0.0,
      "price_is_new": false,
      "quantity_change": -1,
      "first_ed": 0,
      "reverse_holo": 0,
      "archived": false
    },
    {
      "card": "Yamato (OP16-079) (V.2)",
      "canonical_name": "OnePiece_Products_Singles_The-Time-of-Battle-Asia-Region-Legal_Yamato-OP16-079-V2",
      "seller": {
        "name": "Japanstore",
        "country": "Item location: France"
      },
      "language": "Japanese",
      "price": 85.0,
      "quantity": 1,
      "condition": "NM",
      "comment": "",
      "date": 1782108289.4037144,
      "ended": false,
      "new": false,
      "previous_prices": [],
      "previous_quantities": [],
      "first_date": 1781911230.1831412,
      "last_date": 0.0,
      "price_is_new": false,
      "quantity_change": 0,
      "first_ed": 0,
      "reverse_holo": 0,
      "archived": false
    },
    {
      "card": "Yamato (OP16-079) (V.2)",
      "canonical_name": "OnePiece_Products_Singles_The-Time-of-Battle-Asia-Region-Legal_Yamato-OP16-079-V2",
      "seller": {
        "name": "cards-antik",
        "country": "Item location: Germany"
      },
      "language": "Japanese",
      "price": 94.99,
      "quantity": 1,
      "condition": "NM",
      "comment": "",
      "date": 1782108289.4037144,
      "ended": false,
      "new": false,
      "previous_prices": [],
      "previous_quantities": [],
      "first_date": 1781911230.1831412,
      "last_date": 0.0,
      "price_is_new": false,
      "quantity_change": 0,
      "first_ed": 0,
      "reverse_holo": 0,
      "archived": false
    },
    {
      "card": "Yamato (OP16-079) (V.2)",
      "canonical_name": "OnePiece_Products_Singles_The-Time-of-Battle-Asia-Region-Legal_Yamato-OP16-079-V2",
      "seller": {
        "name": "NeroCards",
        "country": "Item location: Germany"
      },
      "language": "Japanese",
      "price": 98.99,
      "quantity": 1,
      "condition": "NM",
      "comment": "",
      "date": 1782108289.4037144,
      "ended": false,
      "new": false,
      "previous_prices": [],
      "previous_quantities": [],
      "first_date": 1781809102.7223003,
      "last_date": 0.0,
      "price_is_new": false,
      "quantity_change": 0,
      "first_ed": 0,
      "reverse_holo": 0,
      "archived": false
    },
    {
      "card": "Yamato (OP16-079) (V.2)",
      "canonical_name": "OnePiece_Products_Singles_The-Time-of-Battle-Asia-Region-Legal_Yamato-OP16-079-V2",
      "seller": {
        "name": "MoziLegends",
        "country": "Item location: Germany"
      },
      "language": "Japanese",
      "price": 99.0,
      "quantity": 1,
      "condition": "NM",
      "comment": "Minimal whitening",
      "date": 1782108289.4037144,
      "ended": false,
      "new": false,
      "previous_prices": [],
      "previous_quantities": [],
      "first_date": 1781809102.7223003,
      "last_date": 0.0,
      "price_is_new": false,
      "quantity_change": 0,
      "first_ed": 0,
      "reverse_holo": 0,
      "archived": false
    },
    {
      "card": "Yamato (OP16-079) (V.2)",
      "canonical_name": "OnePiece_Products_Singles_The-Time-of-Battle-Asia-Region-Legal_Yamato-OP16-079-V2",
      "seller": {
        "name": "ONE-cards",
        "country": "Item location: Germany"
      },
      "language": "Japanese",
      "price": 100.0,
      "quantity": 1,
      "condition": "NM",
      "comment": "From Booster to Sleeve to Toploader",
      "date": 1782108289.4037144,
      "ended": false,
      "new": false,
      "previous_prices": [],
      "previous_quantities": [],
      "first_date": 1781809102.7223003,
      "last_date": 0.0,
      "price_is_new": false,
      "quantity_change": 0,
      "first_ed": 0,
      "reverse_holo": 0,
      "archived": false
    },
    {
      "card": "Yamato (OP16-079) (V.2)",
      "canonical_name": "OnePiece_Products_Singles_The-Time-of-Battle-Asia-Region-Legal_Yamato-OP16-079-V2",
      "seller": {
        "name": "MGMEGAJ",
        "country": "Item location: Italy"
      },
      "language": "Japanese",
      "price": 124.99,
      "quantity": 1,
      "condition": "NM",
      "comment": "",
      "date": 1782108289.4037144,
      "ended": false,
      "new": true,
      "previous_prices": [],
      "previous_quantities": [],
      "first_date": 1782108289.4037144,
      "last_date": 0.0,
      "price_is_new": false,
      "quantity_change": 0,
      "first_ed": 0,
      "reverse_holo": 0,
      "archived": false
    }
  ]
}