{
  "version": "1.0",
  "card": "Umbreon EX  (XY10 082)",
  "set": " Awakening Psychic King - Singles",
  "canonical_name": "Pokemon_Products_Singles_Awakening-Psychic-King_Umbreon-EX-V2",
  "image": "data/images/Pokemon_Products_Singles_Awakening-Psychic-King_Umbreon-EX-V2.jpg",
  "languages": [
    "Japanese",
    "Korean",
    "T-Chinese"
  ],
  "only_germany": "False",
  "available": 6,
  "sold": 0,
  "inserted": 0,
  "listings": [
    {
      "card": "Umbreon EX  (XY10 082)",
      "canonical_name": "Pokemon_Products_Singles_Awakening-Psychic-King_Umbreon-EX-V2",
      "seller": {
        "name": "CardParadise-TV",
        "country": "Item location: Italy"
      },
      "language": "Korean",
      "price": 145.0,
      "quantity": 1,
      "condition": "PO",
      "comment": "",
      "date": 1781855981.4112718,
      "ended": false,
      "new": false,
      "previous_prices": [],
      "previous_quantities": [],
      "first_date": 1771830443.176994,
      "last_date": 0.0,
      "price_is_new": false,
      "quantity_change": 0,
      "first_ed": 0,
      "reverse_holo": 0,
      "archived": false
    },
    {
      "card": "Umbreon EX  (XY10 082)",
      "canonical_name": "Pokemon_Products_Singles_Awakening-Psychic-King_Umbreon-EX-V2",
      "seller": {
        "name": "Dondap94",
        "country": "Item location: Italy"
      },
      "language": "Korean",
      "price": 275.0,
      "quantity": 1,
      "condition": "NM",
      "comment": "GRAAD 8.5",
      "date": 1781855981.4112718,
      "ended": false,
      "new": false,
      "previous_prices": [
        [
          250.0,
          1781608933.1157253
        ],
        [
          215.0,
          1781714711.8104475
        ]
      ],
      "previous_quantities": [],
      "first_date": 1781351479.5206485,
      "last_date": 0.0,
      "price_is_new": true,
      "quantity_change": 0,
      "first_ed": 0,
      "reverse_holo": 0,
      "archived": false
    },
    {
      "card": "Umbreon EX  (XY10 082)",
      "canonical_name": "Pokemon_Products_Singles_Awakening-Psychic-King_Umbreon-EX-V2",
      "seller": {
        "name": "DN-Cards",
        "country": "Item location: Germany"
      },
      "language": "Japanese",
      "price": 299.0,
      "quantity": 1,
      "condition": "PL",
      "comment": "",
      "date": 1781855981.4112718,
      "ended": false,
      "new": false,
      "previous_prices": [],
      "previous_quantities": [],
      "first_date": 1716279486.020848,
      "last_date": 0.0,
      "price_is_new": false,
      "quantity_change": 0,
      "first_ed": 1,
      "reverse_holo": 0,
      "archived": false
    },
    {
      "card": "Umbreon EX  (XY10 082)",
      "canonical_name": "Pokemon_Products_Singles_Awakening-Psychic-King_Umbreon-EX-V2",
      "seller": {
        "name": "Dado68",
        "country": "Item location: France"
      },
      "language": "Japanese",
      "price": 900.0,
      "quantity": 0,
      "condition": "EX",
      "comment": "Ex+ /NM can send a high quality video on dm or instagram (pokeshadow_tcg) negotiate",
      "date": 1776588370.923748,
      "ended": true,
      "new": false,
      "previous_prices": [],
      "previous_quantities": [],
      "first_date": 1771763960.455647,
      "last_date": 0.0,
      "price_is_new": false,
      "quantity_change": 0,
      "first_ed": 0,
      "reverse_holo": 0,
      "archived": false
    },
    {
      "card": "Umbreon EX (XY10 082)",
      "canonical_name": "Pokemon_Products_Singles_Awakening-Psychic-King_Umbreon-EX-V2",
      "seller": {
        "name": "KheZuD2",
        "country": "Item location: Germany"
      },
      "language": "Japanese",
      "price": 1200.0,
      "quantity": 0,
      "condition": "MT",
      "comment": "PSA 9",
      "date": 1725369473.050717,
      "ended": true,
      "new": false,
      "previous_prices": [],
      "previous_quantities": [],
      "first_date": 1717497868.8288314,
      "last_date": 0.0,
      "price_is_new": false,
      "quantity_change": 0,
      "first_ed": 1,
      "reverse_holo": 0,
      "archived": false
    },
    {
      "card": "Umbreon EX  (XY10 082)",
      "canonical_name": "Pokemon_Products_Singles_Awakening-Psychic-King_Umbreon-EX-V2",
      "seller": {
        "name": "ToddBratrud",
        "country": "Item location: Austria"
      },
      "language": "Japanese",
      "price": 1499.99,
      "quantity": 1,
      "condition": "NM",
      "comment": "",
      "date": 1781855981.4112718,
      "ended": false,
      "new": false,
      "previous_prices": [],
      "previous_quantities": [],
      "first_date": 1771830443.176994,
      "last_date": 0.0,
      "price_is_new": false,
      "quantity_change": 0,
      "first_ed": 1,
      "reverse_holo": 0,
      "archived": false
    },
    {
      "card": "Umbreon EX  (XY10 082)",
      "canonical_name": "Pokemon_Products_Singles_Awakening-Psychic-King_Umbreon-EX-V2",
      "seller": {
        "name": "Xavierpika",
        "country": "Item location: France"
      },
      "language": "Japanese",
      "price": 1500.0,
      "quantity": 1,
      "condition": "NM",
      "comment": "PSA 8",
      "date": 1781855981.4112718,
      "ended": false,
      "new": false,
      "previous_prices": [
        [
          1100.0,
          1779166572.9079797
        ],
        [
          850.0,
          1779625477.5540602
        ],
        [
          960.0,
          1780226836.593917
        ]
      ],
      "previous_quantities": [
        [
          1,
          1780303354.8770206
        ],
        [
          0,
          1780303354.8770206
        ]
      ],
      "first_date": 1771763960.455647,
      "last_date": 0.0,
      "price_is_new": false,
      "quantity_change": 0,
      "first_ed": 1,
      "reverse_holo": 0,
      "archived": false
    },
    {
      "card": "Umbreon EX (XY10 082)",
      "canonical_name": "Pokemon_Products_Singles_Awakening-Psychic-King_Umbreon-EX-V2",
      "seller": {
        "name": "Enderworld73",
        "country": "Item location: France"
      },
      "language": "Japanese",
      "price": 1500.0,
      "quantity": 0,
      "condition": "MT",
      "comment": "PCA 9.5",
      "date": 1720783080.2520983,
      "ended": true,
      "new": false,
      "previous_prices": [],
      "previous_quantities": [],
      "first_date": 1716279486.020848,
      "last_date": 0.0,
      "price_is_new": false,
      "quantity_change": 0,
      "first_ed": 1,
      "reverse_holo": 0,
      "archived": false
    },
    {
      "card": "Umbreon EX  (XY10 082)",
      "canonical_name": "Pokemon_Products_Singles_Awakening-Psychic-King_Umbreon-EX-V2",
      "seller": {
        "name": "HHrmn",
        "country": "Item location: Germany"
      },
      "language": "Japanese",
      "price": 1900.0,
      "quantity": 1,
      "condition": "NM",
      "comment": "1. Ed PSA 9 - OBO",
      "date": 1781855981.4112718,
      "ended": false,
      "new": false,
      "previous_prices": [],
      "previous_quantities": [],
      "first_date": 1781520403.264416,
      "last_date": 0.0,
      "price_is_new": false,
      "quantity_change": 0,
      "first_ed": 1,
      "reverse_holo": 0,
      "archived": false
    },
    {
      "card": "Umbreon EX (XY10 082)",
      "canonical_name": "Pokemon_Products_Singles_Awakening-Psychic-King_Umbreon-EX-V2",
      "seller": {
        "name": "KheZuD2",
        "country": "Item location: Germany"
      },
      "language": "Japanese",
      "price": 2000.0,
      "quantity": 0,
      "condition": "NM",
      "comment": "PSA 10",
      "date": 1725369473.050717,
      "ended": true,
      "new": false,
      "previous_prices": [],
      "previous_quantities": [],
      "first_date": 1724669183.8324864,
      "last_date": 0.0,
      "price_is_new": false,
      "quantity_change": 0,
      "first_ed": 0,
      "reverse_holo": 0,
      "archived": false
    },
    {
      "card": "Umbreon EX (XY10 082)",
      "canonical_name": "Pokemon_Products_Singles_Awakening-Psychic-King_Umbreon-EX-V2",
      "seller": {
        "name": "KheZuD2",
        "country": "Item location: Germany"
      },
      "language": "Japanese",
      "price": 2400.0,
      "quantity": 0,
      "condition": "MT",
      "comment": "PSA 10",
      "date": 1725369473.050717,
      "ended": true,
      "new": false,
      "previous_prices": [],
      "previous_quantities": [],
      "first_date": 1717497868.8288314,
      "last_date": 0.0,
      "price_is_new": false,
      "quantity_change": 0,
      "first_ed": 1,
      "reverse_holo": 0,
      "archived": false
    },
    {
      "card": "Umbreon EX (XY10 082)",
      "canonical_name": "Pokemon_Products_Singles_Awakening-Psychic-King_Umbreon-EX-V2",
      "seller": {
        "name": "sosodu74100",
        "country": "Item location: France"
      },
      "language": "Japanese",
      "price": 3200.0,
      "quantity": 0,
      "condition": "MT",
      "comment": "P.S.A 10 ECHANGE/VENTE",
      "date": 1720783080.2520983,
      "ended": true,
      "new": false,
      "previous_prices": [],
      "previous_quantities": [],
      "first_date": 1716881092.4694233,
      "last_date": 0.0,
      "price_is_new": false,
      "quantity_change": 0,
      "first_ed": 1,
      "reverse_holo": 0,
      "archived": false
    },
    {
      "card": "Umbreon EX  (XY10 082)",
      "canonical_name": "Pokemon_Products_Singles_Awakening-Psychic-King_Umbreon-EX-V2",
      "seller": {
        "name": "mijumaru-",
        "country": "Item location: Germany"
      },
      "language": "Japanese",
      "price": 4300.0,
      "quantity": 0,
      "condition": "NM",
      "comment": "RELISTED! PSA 10",
      "date": 1780226836.593917,
      "ended": true,
      "new": false,
      "previous_prices": [
        [
          4999.0,
          1779924616.9765
        ]
      ],
      "previous_quantities": [
        [
          1,
          1777879116.5241253
        ],
        [
          0,
          1777879116.5241253
        ],
        [
          1,
          1779924616.9765
        ],
        [
          0,
          1779924616.9765
        ],
        [
          1,
          1780226836.593917
        ]
      ],
      "first_date": 1775825525.3108943,
      "last_date": 0.0,
      "price_is_new": false,
      "quantity_change": 0,
      "first_ed": 1,
      "reverse_holo": 0,
      "archived": false
    },
    {
      "card": "Umbreon EX  (XY10 082)",
      "canonical_name": "Pokemon_Products_Singles_Awakening-Psychic-King_Umbreon-EX-V2",
      "seller": {
        "name": "Dado68",
        "country": "Item location: France"
      },
      "language": "Japanese",
      "price": 4800.0,
      "quantity": 0,
      "condition": "MT",
      "comment": "PSA 10",
      "date": 1778609156.7265284,
      "ended": true,
      "new": false,
      "previous_prices": [],
      "previous_quantities": [
        [
          1,
          1778609156.7265284
        ]
      ],
      "first_date": 1776720384.259836,
      "last_date": 0.0,
      "price_is_new": false,
      "quantity_change": 0,
      "first_ed": 1,
      "reverse_holo": 0,
      "archived": false
    }
  ]
}